{
  "runId": "20260621-shortlink-redirect-optimized",
  "baseUrl": "http://127.0.0.1:48082",
  "environment": {
    "gitSha": "cfebc1e",
    "gitState": "dirty",
    "javaVersion": "openjdk version 17.0.19 2026-04-21",
    "pythonVersion": "Python 3.9.6",
    "hostName": "linyuxiangdeMacBook-Air.local",
    "deploymentProfile": "local-h2"
  },
  "startedAt": "2026-06-21T11:31:40",
  "finishedAt": "2026-06-21T11:31:43",
  "health": {
    "code": 0,
    "message": "success",
    "data": {
      "status": "UP",
      "time": "2026-06-21T11:31:40.949028+08:00",
      "service": "wuxing-persona-backend"
    }
  },
  "readiness": {
    "code": 0,
    "message": "success",
    "data": {
      "status": "UP",
      "scope": "core_schema",
      "service": "wuxing-persona-backend",
      "time": "2026-06-21T11:31:40.951287+08:00",
      "coreTables": {
        "user_result": "ok",
        "short_link": "ok",
        "visit_event": "ok",
        "site_daily_metric": "ok",
        "short_link_daily_metric": "ok"
      }
    }
  },
  "questionsCount": 5,
  "resultId": "R20260621113141001864949",
  "shortCode": "RJeVXz",
  "workload": "shortlink",
  "syntheticChannel": "perf-test",
  "syntheticCampaign": "performance-limit-test",
  "effectiveSyntheticCampaign": "performance-limit-test:20260621-shortlink-redirect-optimized",
  "allowPublicLoadTest": false,
  "allowRocketMqShadowLoadTest": false,
  "preflightRuntime": {
    "queueSize": 0,
    "queueCapacity": 2048,
    "drainLimit": 64,
    "droppedAsyncEvents": 0,
    "totalFlushedEvents": 0,
    "lastFlushAt": null,
    "lastBatchSize": 0,
    "batchWriteFailures": 0,
    "workerAlive": true,
    "asyncMode": "local",
    "rocketMqAvailable": false,
    "rocketMqFallbackToLocal": true,
    "rocketMqTopic": "wuxing-visit-event",
    "rocketMqPublishedEvents": 0,
    "rocketMqPublishFailures": 0,
    "rocketMqFallbackEvents": 0,
    "rocketMqShadowLocalEvents": 0,
    "rocketMqConsumerEnabled": false,
    "rocketMqConsumerPersistenceReady": false,
    "healthStatus": "ok",
    "healthMessage": "访问事件异步写入正常。"
  },
  "steps": [
    1,
    2,
    4,
    8,
    16,
    32,
    64
  ],
  "requestsPerStage": 128,
  "stopP95Ms": 1200,
  "stopErrorRate": 0.05,
  "stopOnRuntimeDanger": true,
  "strictRuntimeObservation": true,
  "maxQueueUsagePercent": 90.0,
  "maxDroppedAsyncEvents": 0,
  "maxBatchWriteFailures": 0,
  "stageCooldownSeconds": 0.0,
  "stopReason": "completed all stages",
  "analysis": [
    "本轮完成所有阶段，最高 P95 为 179ms，最高错误率为 0.00%。",
    "最高并发阶段最慢接口类型是 `shortlink`，P95 为 179ms，错误数 0。",
    "访问事件运行态未观察到丢弃或批量写失败，最高队列水位 0.00%。",
    "这是短链热路径验证，重点看 302、Location、P95 和访问事件排水，不应直接推导结果页或后台容量。",
    "目标是本机 loopback，结论只能作为本地回归和脚本格式证据；公网容量需要在备案/授权后用真实 Nginx、MySQL、Redis 链路重测。"
  ],
  "stages": [
    {
      "concurrency": 1,
      "requests": 128,
      "ok": 128,
      "errors": 0,
      "errorRate": 0.0,
      "totalMs": 729,
      "rps": 175.58,
      "avgMs": 4.65,
      "p50Ms": 4,
      "p95Ms": 7,
      "p99Ms": 12,
      "runtimeBefore": {
        "queueSize": 0,
        "queueCapacity": 2048,
        "drainLimit": 64,
        "droppedAsyncEvents": 0,
        "totalFlushedEvents": 0,
        "lastFlushAt": null,
        "lastBatchSize": 0,
        "batchWriteFailures": 0,
        "workerAlive": true,
        "asyncMode": "local",
        "rocketMqAvailable": false,
        "rocketMqFallbackToLocal": true,
        "rocketMqTopic": "wuxing-visit-event",
        "rocketMqPublishedEvents": 0,
        "rocketMqPublishFailures": 0,
        "rocketMqFallbackEvents": 0,
        "rocketMqShadowLocalEvents": 0,
        "rocketMqConsumerEnabled": false,
        "rocketMqConsumerPersistenceReady": false,
        "healthStatus": "ok",
        "healthMessage": "访问事件异步写入正常。"
      },
      "runtimeAfter": {
        "queueSize": 0,
        "queueCapacity": 2048,
        "drainLimit": 64,
        "droppedAsyncEvents": 0,
        "totalFlushedEvents": 128,
        "lastFlushAt": "2026-06-21T11:31:41.847681",
        "lastBatchSize": 1,
        "batchWriteFailures": 0,
        "workerAlive": true,
        "asyncMode": "local",
        "rocketMqAvailable": false,
        "rocketMqFallbackToLocal": true,
        "rocketMqTopic": "wuxing-visit-event",
        "rocketMqPublishedEvents": 0,
        "rocketMqPublishFailures": 0,
        "rocketMqFallbackEvents": 0,
        "rocketMqShadowLocalEvents": 0,
        "rocketMqConsumerEnabled": false,
        "rocketMqConsumerPersistenceReady": false,
        "healthStatus": "ok",
        "healthMessage": "访问事件异步写入正常。"
      },
      "runtimeDelta": {
        "totalFlushedEvents": 128,
        "droppedAsyncEvents": 0,
        "batchWriteFailures": 0,
        "rocketMqPublishedEvents": 0,
        "rocketMqFallbackEvents": 0,
        "rocketMqShadowLocalEvents": 0
      },
      "byKind": {
        "shortlink": {
          "requests": 128,
          "ok": 128,
          "errors": 0,
          "avgMs": 4.65,
          "p50Ms": 4,
          "p95Ms": 7,
          "p99Ms": 12,
          "statusCounts": {
            "302": 128
          }
        }
      }
    },
    {
      "concurrency": 2,
      "requests": 128,
      "ok": 128,
      "errors": 0,
      "errorRate": 0.0,
      "totalMs": 450,
      "rps": 284.44,
      "avgMs": 5.86,
      "p50Ms": 5,
      "p95Ms": 10,
      "p99Ms": 15,
      "runtimeBefore": {
        "queueSize": 0,
        "queueCapacity": 2048,
        "drainLimit": 64,
        "droppedAsyncEvents": 0,
        "totalFlushedEvents": 128,
        "lastFlushAt": "2026-06-21T11:31:41.847681",
        "lastBatchSize": 1,
        "batchWriteFailures": 0,
        "workerAlive": true,
        "asyncMode": "local",
        "rocketMqAvailable": false,
        "rocketMqFallbackToLocal": true,
        "rocketMqTopic": "wuxing-visit-event",
        "rocketMqPublishedEvents": 0,
        "rocketMqPublishFailures": 0,
        "rocketMqFallbackEvents": 0,
        "rocketMqShadowLocalEvents": 0,
        "rocketMqConsumerEnabled": false,
        "rocketMqConsumerPersistenceReady": false,
        "healthStatus": "ok",
        "healthMessage": "访问事件异步写入正常。"
      },
      "runtimeAfter": {
        "queueSize": 0,
        "queueCapacity": 2048,
        "drainLimit": 64,
        "droppedAsyncEvents": 0,
        "totalFlushedEvents": 256,
        "lastFlushAt": "2026-06-21T11:31:42.300563",
        "lastBatchSize": 1,
        "batchWriteFailures": 0,
        "workerAlive": true,
        "asyncMode": "local",
        "rocketMqAvailable": false,
        "rocketMqFallbackToLocal": true,
        "rocketMqTopic": "wuxing-visit-event",
        "rocketMqPublishedEvents": 0,
        "rocketMqPublishFailures": 0,
        "rocketMqFallbackEvents": 0,
        "rocketMqShadowLocalEvents": 0,
        "rocketMqConsumerEnabled": false,
        "rocketMqConsumerPersistenceReady": false,
        "healthStatus": "ok",
        "healthMessage": "访问事件异步写入正常。"
      },
      "runtimeDelta": {
        "totalFlushedEvents": 128,
        "droppedAsyncEvents": 0,
        "batchWriteFailures": 0,
        "rocketMqPublishedEvents": 0,
        "rocketMqFallbackEvents": 0,
        "rocketMqShadowLocalEvents": 0
      },
      "byKind": {
        "shortlink": {
          "requests": 128,
          "ok": 128,
          "errors": 0,
          "avgMs": 5.86,
          "p50Ms": 5,
          "p95Ms": 10,
          "p99Ms": 15,
          "statusCounts": {
            "302": 128
          }
        }
      }
    },
    {
      "concurrency": 4,
      "requests": 128,
      "ok": 128,
      "errors": 0,
      "errorRate": 0.0,
      "totalMs": 342,
      "rps": 374.27,
      "avgMs": 9.43,
      "p50Ms": 9,
      "p95Ms": 13,
      "p99Ms": 14,
      "runtimeBefore": {
        "queueSize": 0,
        "queueCapacity": 2048,
        "drainLimit": 64,
        "droppedAsyncEvents": 0,
        "totalFlushedEvents": 256,
        "lastFlushAt": "2026-06-21T11:31:42.300563",
        "lastBatchSize": 1,
        "batchWriteFailures": 0,
        "workerAlive": true,
        "asyncMode": "local",
        "rocketMqAvailable": false,
        "rocketMqFallbackToLocal": true,
        "rocketMqTopic": "wuxing-visit-event",
        "rocketMqPublishedEvents": 0,
        "rocketMqPublishFailures": 0,
        "rocketMqFallbackEvents": 0,
        "rocketMqShadowLocalEvents": 0,
        "rocketMqConsumerEnabled": false,
        "rocketMqConsumerPersistenceReady": false,
        "healthStatus": "ok",
        "healthMessage": "访问事件异步写入正常。"
      },
      "runtimeAfter": {
        "queueSize": 0,
        "queueCapacity": 2048,
        "drainLimit": 64,
        "droppedAsyncEvents": 0,
        "totalFlushedEvents": 384,
        "lastFlushAt": "2026-06-21T11:31:42.645282",
        "lastBatchSize": 1,
        "batchWriteFailures": 0,
        "workerAlive": true,
        "asyncMode": "local",
        "rocketMqAvailable": false,
        "rocketMqFallbackToLocal": true,
        "rocketMqTopic": "wuxing-visit-event",
        "rocketMqPublishedEvents": 0,
        "rocketMqPublishFailures": 0,
        "rocketMqFallbackEvents": 0,
        "rocketMqShadowLocalEvents": 0,
        "rocketMqConsumerEnabled": false,
        "rocketMqConsumerPersistenceReady": false,
        "healthStatus": "ok",
        "healthMessage": "访问事件异步写入正常。"
      },
      "runtimeDelta": {
        "totalFlushedEvents": 128,
        "droppedAsyncEvents": 0,
        "batchWriteFailures": 0,
        "rocketMqPublishedEvents": 0,
        "rocketMqFallbackEvents": 0,
        "rocketMqShadowLocalEvents": 0
      },
      "byKind": {
        "shortlink": {
          "requests": 128,
          "ok": 128,
          "errors": 0,
          "avgMs": 9.43,
          "p50Ms": 9,
          "p95Ms": 13,
          "p99Ms": 14,
          "statusCounts": {
            "302": 128
          }
        }
      }
    },
    {
      "concurrency": 8,
      "requests": 128,
      "ok": 128,
      "errors": 0,
      "errorRate": 0.0,
      "totalMs": 324,
      "rps": 395.06,
      "avgMs": 18.67,
      "p50Ms": 18,
      "p95Ms": 26,
      "p99Ms": 28,
      "runtimeBefore": {
        "queueSize": 0,
        "queueCapacity": 2048,
        "drainLimit": 64,
        "droppedAsyncEvents": 0,
        "totalFlushedEvents": 384,
        "lastFlushAt": "2026-06-21T11:31:42.645282",
        "lastBatchSize": 1,
        "batchWriteFailures": 0,
        "workerAlive": true,
        "asyncMode": "local",
        "rocketMqAvailable": false,
        "rocketMqFallbackToLocal": true,
        "rocketMqTopic": "wuxing-visit-event",
        "rocketMqPublishedEvents": 0,
        "rocketMqPublishFailures": 0,
        "rocketMqFallbackEvents": 0,
        "rocketMqShadowLocalEvents": 0,
        "rocketMqConsumerEnabled": false,
        "rocketMqConsumerPersistenceReady": false,
        "healthStatus": "ok",
        "healthMessage": "访问事件异步写入正常。"
      },
      "runtimeAfter": {
        "queueSize": 0,
        "queueCapacity": 2048,
        "drainLimit": 64,
        "droppedAsyncEvents": 0,
        "totalFlushedEvents": 512,
        "lastFlushAt": "2026-06-21T11:31:42.972244",
        "lastBatchSize": 1,
        "batchWriteFailures": 0,
        "workerAlive": true,
        "asyncMode": "local",
        "rocketMqAvailable": false,
        "rocketMqFallbackToLocal": true,
        "rocketMqTopic": "wuxing-visit-event",
        "rocketMqPublishedEvents": 0,
        "rocketMqPublishFailures": 0,
        "rocketMqFallbackEvents": 0,
        "rocketMqShadowLocalEvents": 0,
        "rocketMqConsumerEnabled": false,
        "rocketMqConsumerPersistenceReady": false,
        "healthStatus": "ok",
        "healthMessage": "访问事件异步写入正常。"
      },
      "runtimeDelta": {
        "totalFlushedEvents": 128,
        "droppedAsyncEvents": 0,
        "batchWriteFailures": 0,
        "rocketMqPublishedEvents": 0,
        "rocketMqFallbackEvents": 0,
        "rocketMqShadowLocalEvents": 0
      },
      "byKind": {
        "shortlink": {
          "requests": 128,
          "ok": 128,
          "errors": 0,
          "avgMs": 18.67,
          "p50Ms": 18,
          "p95Ms": 26,
          "p99Ms": 28,
          "statusCounts": {
            "302": 128
          }
        }
      }
    },
    {
      "concurrency": 16,
      "requests": 128,
      "ok": 128,
      "errors": 0,
      "errorRate": 0.0,
      "totalMs": 318,
      "rps": 402.52,
      "avgMs": 36.52,
      "p50Ms": 38,
      "p95Ms": 46,
      "p99Ms": 53,
      "runtimeBefore": {
        "queueSize": 0,
        "queueCapacity": 2048,
        "drainLimit": 64,
        "droppedAsyncEvents": 0,
        "totalFlushedEvents": 512,
        "lastFlushAt": "2026-06-21T11:31:42.972244",
        "lastBatchSize": 1,
        "batchWriteFailures": 0,
        "workerAlive": true,
        "asyncMode": "local",
        "rocketMqAvailable": false,
        "rocketMqFallbackToLocal": true,
        "rocketMqTopic": "wuxing-visit-event",
        "rocketMqPublishedEvents": 0,
        "rocketMqPublishFailures": 0,
        "rocketMqFallbackEvents": 0,
        "rocketMqShadowLocalEvents": 0,
        "rocketMqConsumerEnabled": false,
        "rocketMqConsumerPersistenceReady": false,
        "healthStatus": "ok",
        "healthMessage": "访问事件异步写入正常。"
      },
      "runtimeAfter": {
        "queueSize": 0,
        "queueCapacity": 2048,
        "drainLimit": 64,
        "droppedAsyncEvents": 0,
        "totalFlushedEvents": 640,
        "lastFlushAt": "2026-06-21T11:31:43.292695",
        "lastBatchSize": 1,
        "batchWriteFailures": 0,
        "workerAlive": true,
        "asyncMode": "local",
        "rocketMqAvailable": false,
        "rocketMqFallbackToLocal": true,
        "rocketMqTopic": "wuxing-visit-event",
        "rocketMqPublishedEvents": 0,
        "rocketMqPublishFailures": 0,
        "rocketMqFallbackEvents": 0,
        "rocketMqShadowLocalEvents": 0,
        "rocketMqConsumerEnabled": false,
        "rocketMqConsumerPersistenceReady": false,
        "healthStatus": "ok",
        "healthMessage": "访问事件异步写入正常。"
      },
      "runtimeDelta": {
        "totalFlushedEvents": 128,
        "droppedAsyncEvents": 0,
        "batchWriteFailures": 0,
        "rocketMqPublishedEvents": 0,
        "rocketMqFallbackEvents": 0,
        "rocketMqShadowLocalEvents": 0
      },
      "byKind": {
        "shortlink": {
          "requests": 128,
          "ok": 128,
          "errors": 0,
          "avgMs": 36.52,
          "p50Ms": 38,
          "p95Ms": 46,
          "p99Ms": 53,
          "statusCounts": {
            "302": 128
          }
        }
      }
    },
    {
      "concurrency": 32,
      "requests": 128,
      "ok": 128,
      "errors": 0,
      "errorRate": 0.0,
      "totalMs": 325,
      "rps": 393.85,
      "avgMs": 72.09,
      "p50Ms": 75,
      "p95Ms": 90,
      "p99Ms": 93,
      "runtimeBefore": {
        "queueSize": 0,
        "queueCapacity": 2048,
        "drainLimit": 64,
        "droppedAsyncEvents": 0,
        "totalFlushedEvents": 640,
        "lastFlushAt": "2026-06-21T11:31:43.292695",
        "lastBatchSize": 1,
        "batchWriteFailures": 0,
        "workerAlive": true,
        "asyncMode": "local",
        "rocketMqAvailable": false,
        "rocketMqFallbackToLocal": true,
        "rocketMqTopic": "wuxing-visit-event",
        "rocketMqPublishedEvents": 0,
        "rocketMqPublishFailures": 0,
        "rocketMqFallbackEvents": 0,
        "rocketMqShadowLocalEvents": 0,
        "rocketMqConsumerEnabled": false,
        "rocketMqConsumerPersistenceReady": false,
        "healthStatus": "ok",
        "healthMessage": "访问事件异步写入正常。"
      },
      "runtimeAfter": {
        "queueSize": 0,
        "queueCapacity": 2048,
        "drainLimit": 64,
        "droppedAsyncEvents": 0,
        "totalFlushedEvents": 768,
        "lastFlushAt": "2026-06-21T11:31:43.620784",
        "lastBatchSize": 1,
        "batchWriteFailures": 0,
        "workerAlive": true,
        "asyncMode": "local",
        "rocketMqAvailable": false,
        "rocketMqFallbackToLocal": true,
        "rocketMqTopic": "wuxing-visit-event",
        "rocketMqPublishedEvents": 0,
        "rocketMqPublishFailures": 0,
        "rocketMqFallbackEvents": 0,
        "rocketMqShadowLocalEvents": 0,
        "rocketMqConsumerEnabled": false,
        "rocketMqConsumerPersistenceReady": false,
        "healthStatus": "ok",
        "healthMessage": "访问事件异步写入正常。"
      },
      "runtimeDelta": {
        "totalFlushedEvents": 128,
        "droppedAsyncEvents": 0,
        "batchWriteFailures": 0,
        "rocketMqPublishedEvents": 0,
        "rocketMqFallbackEvents": 0,
        "rocketMqShadowLocalEvents": 0
      },
      "byKind": {
        "shortlink": {
          "requests": 128,
          "ok": 128,
          "errors": 0,
          "avgMs": 72.09,
          "p50Ms": 75,
          "p95Ms": 90,
          "p99Ms": 93,
          "statusCounts": {
            "302": 128
          }
        }
      }
    },
    {
      "concurrency": 64,
      "requests": 128,
      "ok": 128,
      "errors": 0,
      "errorRate": 0.0,
      "totalMs": 346,
      "rps": 369.94,
      "avgMs": 137.36,
      "p50Ms": 139,
      "p95Ms": 179,
      "p99Ms": 222,
      "runtimeBefore": {
        "queueSize": 0,
        "queueCapacity": 2048,
        "drainLimit": 64,
        "droppedAsyncEvents": 0,
        "totalFlushedEvents": 768,
        "lastFlushAt": "2026-06-21T11:31:43.620784",
        "lastBatchSize": 1,
        "batchWriteFailures": 0,
        "workerAlive": true,
        "asyncMode": "local",
        "rocketMqAvailable": false,
        "rocketMqFallbackToLocal": true,
        "rocketMqTopic": "wuxing-visit-event",
        "rocketMqPublishedEvents": 0,
        "rocketMqPublishFailures": 0,
        "rocketMqFallbackEvents": 0,
        "rocketMqShadowLocalEvents": 0,
        "rocketMqConsumerEnabled": false,
        "rocketMqConsumerPersistenceReady": false,
        "healthStatus": "ok",
        "healthMessage": "访问事件异步写入正常。"
      },
      "runtimeAfter": {
        "queueSize": 0,
        "queueCapacity": 2048,
        "drainLimit": 64,
        "droppedAsyncEvents": 0,
        "totalFlushedEvents": 896,
        "lastFlushAt": "2026-06-21T11:31:43.969553",
        "lastBatchSize": 1,
        "batchWriteFailures": 0,
        "workerAlive": true,
        "asyncMode": "local",
        "rocketMqAvailable": false,
        "rocketMqFallbackToLocal": true,
        "rocketMqTopic": "wuxing-visit-event",
        "rocketMqPublishedEvents": 0,
        "rocketMqPublishFailures": 0,
        "rocketMqFallbackEvents": 0,
        "rocketMqShadowLocalEvents": 0,
        "rocketMqConsumerEnabled": false,
        "rocketMqConsumerPersistenceReady": false,
        "healthStatus": "ok",
        "healthMessage": "访问事件异步写入正常。"
      },
      "runtimeDelta": {
        "totalFlushedEvents": 128,
        "droppedAsyncEvents": 0,
        "batchWriteFailures": 0,
        "rocketMqPublishedEvents": 0,
        "rocketMqFallbackEvents": 0,
        "rocketMqShadowLocalEvents": 0
      },
      "byKind": {
        "shortlink": {
          "requests": 128,
          "ok": 128,
          "errors": 0,
          "avgMs": 137.36,
          "p50Ms": 139,
          "p95Ms": 179,
          "p99Ms": 222,
          "statusCounts": {
            "302": 128
          }
        }
      }
    }
  ]
}